aioblitzkrieg/__init__.py
aioblitzkrieg/api.py
aioblitzkrieg/base.py
aioblitzkrieg/exceptions.py
aioblitzkrieg/models/__init__.py
aioblitzkrieg/models/archives.py
aioblitzkrieg/models/other.py
aioblitzkrieg/models/sellers.py
aioblitzkrieg-0.2.dist-info/METADATA
aioblitzkrieg-0.2.dist-info/WHEEL
aioblitzkrieg-0.2.dist-info/top_level.txt
aioblitzkrieg-0.2.dist-info/RECORD
